odoo/addons/partner_last_invoice_date/README.rst
odoo/addons/partner_last_invoice_date/__init__.py
odoo/addons/partner_last_invoice_date/__manifest__.py
odoo/addons/partner_last_invoice_date/hooks.py
odoo/addons/partner_last_invoice_date/i18n/es.po
odoo/addons/partner_last_invoice_date/i18n/it.po
odoo/addons/partner_last_invoice_date/i18n/partner_last_invoice_date.pot
odoo/addons/partner_last_invoice_date/models/__init__.py
odoo/addons/partner_last_invoice_date/models/res_partner.py
odoo/addons/partner_last_invoice_date/readme/CONTRIBUTORS.rst
odoo/addons/partner_last_invoice_date/readme/DESCRIPTION.rst
odoo/addons/partner_last_invoice_date/static/description/icon.png
odoo/addons/partner_last_invoice_date/static/description/index.html
odoo/addons/partner_last_invoice_date/tests/__init__.py
odoo/addons/partner_last_invoice_date/tests/test_partner_last_invoice_date.py
odoo/addons/partner_last_invoice_date/views/res_partner_views.xml
odoo_addon_partner_last_invoice_date-16.0.1.0.1.dist-info/METADATA
odoo_addon_partner_last_invoice_date-16.0.1.0.1.dist-info/WHEEL
odoo_addon_partner_last_invoice_date-16.0.1.0.1.dist-info/top_level.txt
odoo_addon_partner_last_invoice_date-16.0.1.0.1.dist-info/RECORD
